adaptdl_ray/__init__.py
adaptdl_ray/adaptdl/__init__.py
adaptdl_ray/adaptdl/adaptdl_allocator.py
adaptdl_ray/adaptdl/adaptdl_job_mixin.py
adaptdl_ray/adaptdl/config.py
adaptdl_ray/adaptdl/config_test.py
adaptdl_ray/adaptdl/utils.py
adaptdl_ray/aws/__init__.py
adaptdl_ray/aws/_example_worker.py
adaptdl_ray/aws/_test_setup.py
adaptdl_ray/aws/controller.py
adaptdl_ray/aws/launch_job.py
adaptdl_ray/aws/optimizer.py
adaptdl_ray/aws/test_controller.py
adaptdl_ray/aws/test_controller_mocked_ray.py
adaptdl_ray/aws/test_worker.py
adaptdl_ray/aws/utils.py
adaptdl_ray/aws/worker.py
adaptdl_ray/tune/__init__.py
adaptdl_ray/tune/adaptdl_patch.py
adaptdl_ray/tune/adaptdl_trainable.py
adaptdl_ray/tune/adaptdl_trainable_test.py
adaptdl_ray/tune/adaptdl_trial.py
adaptdl_ray/tune/adaptdl_trial_sched.py
adaptdl_ray/tune/adaptdl_trial_test.py
adaptdl_ray-0.2.11.dist-info/METADATA
adaptdl_ray-0.2.11.dist-info/WHEEL
adaptdl_ray-0.2.11.dist-info/entry_points.txt
adaptdl_ray-0.2.11.dist-info/top_level.txt
adaptdl_ray-0.2.11.dist-info/RECORD
